urdf2mjcf/__init__.py
urdf2mjcf/convert.py
urdf2mjcf/model.py
urdf2mjcf/py.typed
urdf2mjcf/utils.py
urdf2mjcf/postprocess/__init__.py
urdf2mjcf/postprocess/add_backlash.py
urdf2mjcf/postprocess/add_floor.py
urdf2mjcf/postprocess/add_sensors.py
urdf2mjcf/postprocess/base_joint.py
urdf2mjcf/postprocess/collisions.py
urdf2mjcf/postprocess/explicit_floor_contacts.py
urdf2mjcf/postprocess/make_degrees.py
urdf2mjcf/postprocess/remove_redundancies.py
urdf2mjcf-0.2.37.dist-info/licenses/LICENSE
urdf2mjcf-0.2.37.dist-info/METADATA
urdf2mjcf-0.2.37.dist-info/WHEEL
urdf2mjcf-0.2.37.dist-info/entry_points.txt
urdf2mjcf-0.2.37.dist-info/top_level.txt
urdf2mjcf-0.2.37.dist-info/RECORD
