Metadata-Version: 2.4
Name: urdf2mjcf
Version: 0.2.37
Summary: The urdf2mjcf project
Home-page: https://github.com/kscalelabs/urdf2mjcf
Author: Benjamin Bolte
Requires-Python: >=3.11
License-File: LICENSE
Requires-Dist: colorlogging
Requires-Dist: mujoco
Requires-Dist: numpy
Requires-Dist: pydantic
Requires-Dist: scipy
Requires-Dist: trimesh
Provides-Extra: dev
Requires-Dist: black; extra == "dev"
Requires-Dist: darglint; extra == "dev"
Requires-Dist: mypy; extra == "dev"
Requires-Dist: pytest; extra == "dev"
Requires-Dist: ruff; extra == "dev"
Dynamic: author
Dynamic: description
Dynamic: description-content-type
Dynamic: home-page
Dynamic: license-file
Dynamic: provides-extra
Dynamic: requires-dist
Dynamic: requires-python
Dynamic: summary
